odoo/addons/partner_stage_only_confirmed/README.rst
odoo/addons/partner_stage_only_confirmed/__init__.py
odoo/addons/partner_stage_only_confirmed/__manifest__.py
odoo/addons/partner_stage_only_confirmed/i18n/it.po
odoo/addons/partner_stage_only_confirmed/i18n/partner_stage_only_confirmed.pot
odoo/addons/partner_stage_only_confirmed/models/__init__.py
odoo/addons/partner_stage_only_confirmed/models/base.py
odoo/addons/partner_stage_only_confirmed/readme/CONFIGURATION.rst
odoo/addons/partner_stage_only_confirmed/readme/CONTRIBUTORS.md
odoo/addons/partner_stage_only_confirmed/readme/DESCRIPTION.md
odoo/addons/partner_stage_only_confirmed/readme/USAGE.md
odoo/addons/partner_stage_only_confirmed/static/description/icon.png
odoo/addons/partner_stage_only_confirmed/static/description/index.html
odoo_addon_partner_stage_only_confirmed-17.0.1.1.0.dist-info/METADATA
odoo_addon_partner_stage_only_confirmed-17.0.1.1.0.dist-info/WHEEL
odoo_addon_partner_stage_only_confirmed-17.0.1.1.0.dist-info/top_level.txt
odoo_addon_partner_stage_only_confirmed-17.0.1.1.0.dist-info/RECORD
