Metadata-Version: 2.1
Name: odoo-addon-partner_stage_only_confirmed
Version: 17.0.1.1.0
Requires-Python: >=3.10
Requires-Dist: odoo-addon-partner_stage>=17.0dev,<17.1dev
Requires-Dist: odoo>=17.0a,<17.1dev
Summary: Adds filters on form views to display only confirmed partners
Home-page: https://github.com/OCA/partner-contact
License: AGPL-3
Author: Odoo Community Association (OCA), Camptocamp
Author-email: support@odoo-community.org
Classifier: Programming Language :: Python
Classifier: Framework :: Odoo
Classifier: Framework :: Odoo :: 17.0
Classifier: License :: OSI Approved :: GNU Affero General Public License v3
